configer
