Metadata-Version: 2.1
Name: configer
Version: 1.3.0
Summary: Easy configuration of arguments in a python code!
Home-page: https://github.com/nimagbani/configer
Author: Nima Ghorbani
Author-email: nima.gbani@gmail.com
Maintainer: Nima Ghorbani
Maintainer-email: nima.gbani@gmail.com
License: GNU Affero General Public License, version 3
Platform: UNKNOWN
Classifier: Intended Audience :: Developers
Classifier: License :: OSI Approved :: GNU General Public License v3 (GPLv3)
Classifier: Natural Language :: English
Classifier: Operating System :: MacOS :: MacOS X
Classifier: Operating System :: POSIX
Classifier: Operating System :: POSIX :: BSD
Classifier: Operating System :: POSIX :: Linux
Classifier: Operating System :: Microsoft :: Windows
Classifier: Programming Language :: Python
Classifier: Programming Language :: Python :: 2
Classifier: Programming Language :: Python :: 2.7
Classifier: Programming Language :: Python :: 3
Classifier: Programming Language :: Python :: 3.7
